autocompleter/__init__.py
autocompleter/apps.py
autocompleter/base.py
autocompleter/registry.py
autocompleter/settings.py
autocompleter/urls.py
autocompleter/utils.py
autocompleter/views.py
autocompleter/management/__init__.py
autocompleter/management/commands/__init__.py
autocompleter/management/commands/autocompleter_init.py
django_redis_autocompleter-1.1.3.dist-info/METADATA
django_redis_autocompleter-1.1.3.dist-info/WHEEL
django_redis_autocompleter-1.1.3.dist-info/top_level.txt
django_redis_autocompleter-1.1.3.dist-info/RECORD
