Metadata-Version: 2.4
Name: django-redis-autocompleter
Version: 1.1.3
Summary: A redis-backed autocompleter for Django projects.
Author-email: Ara Anjargolian <ara818@gmail.com>, Kevin Fox <kevin_fox@me.com>
Project-URL: Homepage, https://github.com/ycharts/django-autocompleter
Project-URL: Bug Tracker, https://github.com/ycharts/django-autocompleter/issues
Keywords: autocompleter,django
Classifier: Programming Language :: Python :: 3
Classifier: Environment :: Web Environment
Classifier: Intended Audience :: Developers
Classifier: Operating System :: OS Independent
Classifier: Framework :: Django
Requires-Python: >=3.7
Requires-Dist: Django<6.0,>=3.2.0
Requires-Dist: hiredis>=1
Requires-Dist: redis>=3
